browsergui-0.4.dist-info/DESCRIPTION.rst
browsergui-0.4.dist-info/RECORD
browsergui-0.4.dist-info/METADATA
browsergui-0.4.dist-info/top_level.txt
browsergui-0.4.dist-info/metadata.json
browsergui-0.4.dist-info/WHEEL
browsergui/__init__.py
browsergui/_pythoncompatibility.py
browsergui/_gui.py
browsergui/_documentchangetracker.py
browsergui/elements/_styler.py
browsergui/elements/__init__.py
browsergui/elements/_xmltagshield.py
browsergui/elements/_callbacksetter.py
browsergui/elements/_input/_numberfield.py
browsergui/elements/_input/_bigtextfield.py
browsergui/elements/_input/_inputfield.py
browsergui/elements/_input/_slider.py
browsergui/elements/_input/__init__.py
browsergui/elements/_input/_dropdown.py
browsergui/elements/_input/_valuedelement.py
browsergui/elements/_input/_button.py
browsergui/elements/_input/_textfield.py
browsergui/elements/_input/_colorfield.py
browsergui/elements/_input/_datefield.py
browsergui/elements/_basic/__init__.py
browsergui/elements/_basic/_image.py
browsergui/elements/_basic/_text.py
browsergui/elements/_layout/_container.py
browsergui/elements/_layout/__init__.py
browsergui/elements/_layout/_grid.py
browsergui/elements/_layout/_list.py
browsergui/elements/_layout/_viewport.py
browsergui/_server/__init__.py
browsergui/_server/index.html
browsergui/_server/puppet.js
browsergui/events/__init__.py
browsergui/examples/longrunning.py
browsergui/examples/tour.py
browsergui/examples/minesweeper.py
browsergui/examples/__init__.py
browsergui/examples/__main__.py
browsergui/examples/interactive.py
browsergui/examples/helloworld.py
browsergui/examples/tour-image.png
browsergui/examples/clock.py
