Metadata-Version: 2.0
Name: browsergui
Version: 0.4
Summary: A GUI toolkit targeting browsers
Home-page: https://github.com/speezepearson/browsergui
Author: speezepearson
Author-email: speeze.pearson+1097@gmail.com
License: UNKNOWN
Keywords: browser gui
Platform: UNKNOWN
Classifier: Development Status :: 4 - Beta
Classifier: Intended Audience :: Developers
Classifier: Topic :: Software Development :: User Interfaces
Classifier: Programming Language :: Python :: 2.7
Classifier: Programming Language :: Python :: 3
Classifier: Programming Language :: Python :: 3.2
Classifier: Programming Language :: Python :: 3.3
Classifier: Programming Language :: Python :: 3.4
Provides-Extra: dev
Provides-Extra: test
